{
  "libVersion": "3.11.3",
  "projectname": "%E6%88%90%E9%95%BF%E6%97%B6%E5%85%89%E7%9B%92",
  "condition": {
    "miniprogram": {
      "list": [
        {
          "name": "pages/add-record/add-record",
          "pathName": "pages/add-record/add-record",
          "query": "",
          "scene": null,
          "launchMode": "default"
        }
      ]
    }
  },
  "setting": {
    "urlCheck": false,
    "coverView": true,
    "lazyloadPlaceholderEnable": false,
    "skylineRenderEnable": false,
    "preloadBackgroundData": false,
    "autoAudits": false,
    "useApiHook": true,
    "useApiHostProcess": true,
    "showShadowRootInWxmlPanel": true,
    "useStaticServer": false,
    "useLanDebug": false,
    "showES6CompileOption": false,
    "compileHotReLoad": true,
    "checkInvalidKey": true,
    "ignoreDevUnusedFiles": true,
    "bigPackageSizeSupport": false,
    "useIsolateContext": true
  }
}